pabot/SharedLibrary.py
pabot/__init__.py
pabot/arguments.py
pabot/clientwrapper.py
pabot/coordinatorwrapper.py
pabot/execution_items.py
pabot/pabot.py
pabot/pabotlib.py
pabot/result_merger.py
pabot/robotremoteserver.py
pabot/workerwrapper.py
pabot/py3/__init__.py
pabot/py3/client.py
pabot/py3/coordinator.py
pabot/py3/messages.py
pabot/py3/worker.py
robotframework_pabot-5.1.0.dist-info/licenses/LICENSE.txt
robotframework_pabot-5.1.0.dist-info/METADATA
robotframework_pabot-5.1.0.dist-info/WHEEL
robotframework_pabot-5.1.0.dist-info/entry_points.txt
robotframework_pabot-5.1.0.dist-info/top_level.txt
robotframework_pabot-5.1.0.dist-info/RECORD
