Metadata-Version: 2.4
Name: robotframework-pabot
Version: 5.1.0
Summary: Parallel test runner for Robot Framework
Home-page: https://pabot.org
Download-URL: https://pypi.python.org/pypi/robotframework-pabot
Author: Mikko Korpela
Author-email: mikko.korpela@gmail.com
License: Apache License, Version 2.0
Project-URL: Source, https://github.com/mkorpela/pabot
Classifier: Intended Audience :: Developers
Classifier: Natural Language :: English
Classifier: Programming Language :: Python :: 3
Classifier: Topic :: Software Development :: Testing
Classifier: License :: OSI Approved :: Apache Software License
Classifier: Development Status :: 5 - Production/Stable
Classifier: Framework :: Robot Framework
Requires-Python: >=3.6
License-File: LICENSE.txt
Requires-Dist: robotframework>=3.2
Requires-Dist: robotframework-stacktrace>=0.4.1
Requires-Dist: natsort>=8.2.0
Dynamic: download-url
Dynamic: license-file
